idtap_api/__init__.py
idtap_api/audio_models.py
idtap_api/auth.py
idtap_api/client.py
idtap_api/enums.py
idtap_api/py.typed
idtap_api/secure_storage.py
idtap_api/utils.py
idtap_api/classes/__init__.py
idtap_api/classes/articulation.py
idtap_api/classes/assemblage.py
idtap_api/classes/automation.py
idtap_api/classes/chikari.py
idtap_api/classes/group.py
idtap_api/classes/meter.py
idtap_api/classes/note_view_phrase.py
idtap_api/classes/phrase.py
idtap_api/classes/piece.py
idtap_api/classes/pitch.py
idtap_api/classes/raga.py
idtap_api/classes/section.py
idtap_api/classes/trajectory.py
idtap_api/tests/articulation_test.py
idtap_api/tests/assemblage_test.py
idtap_api/tests/auth_logout_test.py
idtap_api/tests/auth_test.py
idtap_api/tests/automation_test.py
idtap_api/tests/chikari_test.py
idtap_api/tests/client_test.py
idtap_api/tests/group_test.py
idtap_api/tests/meter_test.py
idtap_api/tests/note_view_phrase_test.py
idtap_api/tests/phrase_test.py
idtap_api/tests/piece_test.py
idtap_api/tests/pitch_test.py
idtap_api/tests/raga_test.py
idtap_api/tests/section_test.py
idtap_api/tests/trajectory_test.py
idtap_api-0.1.4.dist-info/licenses/LICENSE
idtap_api-0.1.4.dist-info/METADATA
idtap_api-0.1.4.dist-info/WHEEL
idtap_api-0.1.4.dist-info/top_level.txt
idtap_api-0.1.4.dist-info/RECORD
