Metadata-Version: 2.4
Name: idtap-api
Version: 0.1.4
Summary: Python client library for IDTAP - Interactive Digital Transcription and Analysis Platform for Hindustani music
Author-email: Jon Myers <jon@swara.studio>
Maintainer-email: Jon Myers <jon@swara.studio>
License: MIT
Project-URL: Homepage, https://swara.studio
Project-URL: Documentation, https://github.com/UCSC-IDTAP/Python-API
Project-URL: Repository, https://github.com/UCSC-IDTAP/Python-API
Project-URL: Bug Tracker, https://github.com/UCSC-IDTAP/Python-API/issues
Keywords: music,transcription,hindustani,indian-classical,musicology,ethnomusicology,raga,pitch-analysis,audio-analysis
Classifier: Development Status :: 4 - Beta
Classifier: Intended Audience :: Science/Research
Classifier: Intended Audience :: Developers
Classifier: Topic :: Multimedia :: Sound/Audio :: Analysis
Classifier: Topic :: Scientific/Engineering :: Information Analysis
Classifier: Topic :: Software Development :: Libraries :: Python Modules
Classifier: License :: OSI Approved :: MIT License
Classifier: Programming Language :: Python :: 3
Classifier: Programming Language :: Python :: 3.10
Classifier: Programming Language :: Python :: 3.11
Classifier: Programming Language :: Python :: 3.12
Classifier: Operating System :: OS Independent
Requires-Python: >=3.10
License-File: LICENSE
Requires-Dist: requests>=2.31.0
Requires-Dist: requests-toolbelt>=1.0.0
Requires-Dist: pyhumps>=3.8.0
Requires-Dist: keyring>=24.0.0
Requires-Dist: cryptography>=41.0.0
Requires-Dist: PyJWT>=2.8.0
Requires-Dist: google-auth-oauthlib>=1.0.0
Requires-Dist: pymongo>=4.0.0
Provides-Extra: dev
Requires-Dist: pytest>=7.0.0; extra == "dev"
Requires-Dist: responses>=0.23.0; extra == "dev"
Requires-Dist: black>=23.0.0; extra == "dev"
Requires-Dist: isort>=5.12.0; extra == "dev"
Requires-Dist: mypy>=1.0.0; extra == "dev"
Requires-Dist: flake8>=6.0.0; extra == "dev"
Provides-Extra: linux
Requires-Dist: secretstorage>=3.3.0; extra == "linux"
Dynamic: license-file
